simplecalculatorpaulit/__init__.py
simplecalculatorpaulit/__main__.py
simplecalculatorpaulit/simplecalculatorpaulit.py
simplecalculatorpaulit-1.0.0.dist-info/LICENSE
simplecalculatorpaulit-1.0.0.dist-info/METADATA
simplecalculatorpaulit-1.0.0.dist-info/WHEEL
simplecalculatorpaulit-1.0.0.dist-info/top_level.txt
simplecalculatorpaulit-1.0.0.dist-info/RECORD
