Metadata-Version: 2.1
Name: simplecalculatorpaulit
Version: 1.0.0
Summary: A simple calculator module for arithmetic, scientific, and statistical operations
Home-page: https://github.com/paulit00/simplecalculatorpaulit
Author: Paulius Litvinas
Author-email: Paulius Litvinas <paulit@ktu.lt>
Project-URL: Home, https://github.com/paulit00/simplecalculatorpaulit
Classifier: License :: OSI Approved :: MIT License
Requires-Python: >=3.6
License-File: LICENSE
